LICENSE
MANIFEST.in
README.rst
setup.cfg
setup.py
ukpostcodevalidator/__init__.py
ukpostcodevalidator/validator.py
ukpostcodevalidator.egg-info/PKG-INFO
ukpostcodevalidator.egg-info/SOURCES.txt
ukpostcodevalidator.egg-info/dependency_links.txt
ukpostcodevalidator.egg-info/requires.txt
ukpostcodevalidator.egg-info/top_level.txt