Metadata-Version: 1.0
Name: ukpostcodevalidator
Version: 0.1.4
Summary: validates uk postal code
Home-page: http://github.com/eddmash/ukpostcodevalidator
Author: Eddilbert Macharia
Author-email: edd.cowan@gmail.com
License: MIT
Platform: UNKNOWN
